crossbar/LICENSE
crossbar/LICENSES-OSS
crossbar/__init__.py
crossbar/_compat.py
crossbar/_log_categories.py
crossbar/_logging.py
crossbar/_util.py
crossbar/_version.py
crossbar/interfaces.py
crossbar/personality.py
crossbar/py.typed
crossbar/bridge/__init__.py
crossbar/bridge/mqtt/__init__.py
crossbar/bridge/mqtt/_events.py
crossbar/bridge/mqtt/_utils.py
crossbar/bridge/mqtt/protocol.py
crossbar/bridge/mqtt/tx.py
crossbar/bridge/mqtt/wamp.py
crossbar/bridge/mqtt/test/__init__.py
crossbar/bridge/mqtt/test/interop.py
crossbar/bridge/mqtt/test/interop_tests.py
crossbar/bridge/mqtt/test/test_events.py
crossbar/bridge/mqtt/test/test_protocol.py
crossbar/bridge/mqtt/test/test_topic.py
crossbar/bridge/mqtt/test/test_tx.py
crossbar/bridge/mqtt/test/test_wamp.py
crossbar/bridge/mqtt/test/certs/ca.cert.pem
crossbar/bridge/mqtt/test/certs/client.crt
crossbar/bridge/mqtt/test/certs/client.key
crossbar/bridge/mqtt/test/certs/client_1.crt
crossbar/bridge/mqtt/test/certs/client_1.key
crossbar/bridge/mqtt/test/certs/dhparam
crossbar/bridge/mqtt/test/certs/intermediate.cert.pem
crossbar/bridge/mqtt/test/certs/server.crt
crossbar/bridge/mqtt/test/certs/server.key
crossbar/bridge/rest/__init__.py
crossbar/bridge/rest/callee.py
crossbar/bridge/rest/caller.py
crossbar/bridge/rest/common.py
crossbar/bridge/rest/publisher.py
crossbar/bridge/rest/subscriber.py
crossbar/bridge/rest/webhook.py
crossbar/bridge/rest/test/__init__.py
crossbar/bridge/rest/test/_request.py
crossbar/bridge/rest/test/test_callee.py
crossbar/bridge/rest/test/test_caller.py
crossbar/bridge/rest/test/test_common.py
crossbar/bridge/rest/test/test_publisher.py
crossbar/bridge/rest/test/test_signature.py
crossbar/bridge/rest/test/test_subscriber.py
crossbar/bridge/rest/test/test_webhook.py
crossbar/common/__init__.py
crossbar/common/checkconfig.py
crossbar/common/fswatcher.py
crossbar/common/key.py
crossbar/common/monitor.py
crossbar/common/process.py
crossbar/common/processinfo.py
crossbar/common/profiler.py
crossbar-25.12.1.dist-info/METADATA
crossbar-25.12.1.dist-info/WHEEL
crossbar-25.12.1.dist-info/entry_points.txt
crossbar-25.12.1.dist-info/licenses/LICENSE
crossbar-25.12.1.dist-info/RECORD
