Metadata-Version: 2.4
Name: crossbar
Version: 25.12.1
Summary: Crossbar.io multi-protocol (WAMP/WebSocket, REST/HTTP, MQTT) application router for microservices.
Project-URL: Homepage, https://crossbar.io
Project-URL: Documentation, https://crossbar.io/docs/
Project-URL: Repository, https://github.com/crossbario/crossbar
Project-URL: Issues, https://github.com/crossbario/crossbar/issues
Project-URL: Forum, https://crossbar.discourse.group/
Author: typedef int GmbH
License-Expression: EUPL-1.2
License-File: LICENSE
Keywords: autobahn,autobahn.ws,crossbar,oracle,postgres,postgresql,pubsub,realtime,rfc6455,router,rpc,wamp,websocket
Classifier: Development Status :: 5 - Production/Stable
Classifier: Environment :: Console
Classifier: Environment :: No Input/Output (Daemon)
Classifier: Framework :: Twisted
Classifier: Intended Audience :: Developers
Classifier: Operating System :: OS Independent
Classifier: Programming Language :: Python
Classifier: Programming Language :: Python :: 3
Classifier: Programming Language :: Python :: 3.11
Classifier: Programming Language :: Python :: 3.12
Classifier: Programming Language :: Python :: 3.13
Classifier: Programming Language :: Python :: 3.14
Classifier: Programming Language :: Python :: Implementation :: CPython
Classifier: Programming Language :: Python :: Implementation :: PyPy
Classifier: Topic :: Communications
Classifier: Topic :: Database
Classifier: Topic :: Home Automation
Classifier: Topic :: Internet
Classifier: Topic :: Internet :: WWW/HTTP :: HTTP Servers
Classifier: Topic :: Software Development :: Embedded Systems
Classifier: Topic :: Software Development :: Libraries
Classifier: Topic :: Software Development :: Libraries :: Application Frameworks
Classifier: Topic :: Software Development :: Object Brokering
Classifier: Topic :: System :: Distributed Computing
Classifier: Topic :: System :: Networking
Requires-Python: >=3.11
Requires-Dist: attrs>=22.2.0
Requires-Dist: autobahn[compress,encryption,scram,serialization,twisted]>=25.12.2
Requires-Dist: base58>=2.1.1
Requires-Dist: bcrypt>=4.0.1
Requires-Dist: bitstring>=4.0.1
Requires-Dist: cbor2>=5.4.6
Requires-Dist: cfxdb>=25.12.2
Requires-Dist: click>=8.1.3
Requires-Dist: colorama>=0.4.6
Requires-Dist: constantly>=15.1.0
Requires-Dist: cookiecutter>=2.1.1
Requires-Dist: cryptography>=39.0.0
Requires-Dist: docker>=6.0.1
Requires-Dist: eth-abi<5.2.0,>=5.1.0
Requires-Dist: eth-account>=0.13.0
Requires-Dist: eth-typing>=5.0.1
Requires-Dist: flask>=2.2.2
Requires-Dist: h2<4.0.0,>=3.2.0
Requires-Dist: hexbytes>=0.3.0
Requires-Dist: humanize>=4.4.0
Requires-Dist: hyperframe<6.0.0,>=5.2.0
Requires-Dist: idna<2.6,>=2.5
Requires-Dist: importlib-resources>=5.10.2
Requires-Dist: incremental>=22.10.0
Requires-Dist: iso8601>=1.1.0
Requires-Dist: jinja2-highlight>=0.6.1
Requires-Dist: jinja2>=3.1.2
Requires-Dist: jsonschema>=4.0.0
Requires-Dist: markupsafe>=2.1.2
Requires-Dist: mistune>=2.0.4
Requires-Dist: morphys>=1.0
Requires-Dist: netaddr>=0.8.0
Requires-Dist: numpy>=1.24.1
Requires-Dist: parsimonious<0.11.0,>=0.9.0
Requires-Dist: passlib>=1.7.4
Requires-Dist: priority<2.0,>=1.3.0
Requires-Dist: prompt-toolkit>=3.0.36
Requires-Dist: psutil>=5.9.4
Requires-Dist: py-eth-sig-utils>=0.4.0
Requires-Dist: py-ubjson>=0.16.1
Requires-Dist: pyasn1-modules>=0.2.8
Requires-Dist: pyasn1>=0.4.8
Requires-Dist: pycryptodome>=3.16.0
Requires-Dist: pygments>=2.14.0
Requires-Dist: pynacl>=1.5.0
Requires-Dist: pyopenssl>=23.0.0
Requires-Dist: pyqrcode>=1.2.1
Requires-Dist: pytrie>=0.4.0
Requires-Dist: pyyaml>=6.0
Requires-Dist: requests>=2.28.2
Requires-Dist: sdnotify>=0.3.2
Requires-Dist: service-identity>=21.1.0
Requires-Dist: setproctitle>=1.3.2
Requires-Dist: setuptools>=67.2.0
Requires-Dist: six>=1.16.0
Requires-Dist: sortedcontainers>=2.4.0
Requires-Dist: stringcase>=1.2.0
Requires-Dist: tabulate>=0.9.0
Requires-Dist: treq>=22.2.0
Requires-Dist: twisted[conch,http2,osx-platform,tls]>=22.10.0; sys_platform == 'darwin'
Requires-Dist: twisted[conch,http2,tls,windows-platform]>=22.10.0; sys_platform == 'win32'
Requires-Dist: twisted[conch,http2,tls]>=22.10.0; sys_platform != 'darwin' and sys_platform != 'win32'
Requires-Dist: txaio>=25.12.2
Requires-Dist: txtorcon>=22.0.0
Requires-Dist: u-msgpack-python>=2.7.2
Requires-Dist: ujson>=5.7.0
Requires-Dist: urllib3<1.27,>=1.26.14
Requires-Dist: validate-email>=1.3
Requires-Dist: watchdog>=2.2.1
Requires-Dist: werkzeug>=2.2.2
Requires-Dist: wsaccel>=0.6.4; platform_python_implementation == 'CPython'
Requires-Dist: xbr>=25.12.2
Requires-Dist: zlmdb>=25.12.3
Requires-Dist: zope-interface>=5.5.2
Provides-Extra: dev
Requires-Dist: bandit; extra == 'dev'
Requires-Dist: build>=1.0.0; extra == 'dev'
Requires-Dist: furo>=2024.1.29; extra == 'dev'
Requires-Dist: hashin; extra == 'dev'
Requires-Dist: humanize>=4.0.0; extra == 'dev'
Requires-Dist: jinja2>=3.1.2; extra == 'dev'
Requires-Dist: mock; extra == 'dev'
Requires-Dist: nbsphinx>=0.8.8; extra == 'dev'
Requires-Dist: pandoc>=2.1; extra == 'dev'
Requires-Dist: pip-licenses>=3.5.3; extra == 'dev'
Requires-Dist: pip>=23.0; extra == 'dev'
Requires-Dist: pyenchant>=3.2.2; extra == 'dev'
Requires-Dist: pygments>=2.11.2; extra == 'dev'
Requires-Dist: pyinstaller>=4.2; extra == 'dev'
Requires-Dist: pytest-cov; extra == 'dev'
Requires-Dist: pytest-tap; extra == 'dev'
Requires-Dist: pytest-twisted; extra == 'dev'
Requires-Dist: pytest>=7.2.1; extra == 'dev'
Requires-Dist: ruff>=0.1.0; extra == 'dev'
Requires-Dist: scour>=0.38; extra == 'dev'
Requires-Dist: setuptools>=67.2.0; extra == 'dev'
Requires-Dist: sphinx-autodoc-typehints>=1.17.0; extra == 'dev'
Requires-Dist: sphinx>=6.1.3; extra == 'dev'
Requires-Dist: sphinxcontrib-images>=0.9.4; extra == 'dev'
Requires-Dist: sphinxcontrib-spelling>=7.3.2; extra == 'dev'
Requires-Dist: tap-py; extra == 'dev'
Requires-Dist: tox>=4.2.8; extra == 'dev'
Requires-Dist: twine; extra == 'dev'
Requires-Dist: wheel; extra == 'dev'
Provides-Extra: dev-local
Provides-Extra: docs
Requires-Dist: furo>=2024.7.0; extra == 'docs'
Requires-Dist: linkify-it-py>=2.0.0; extra == 'docs'
Requires-Dist: myst-parser>=2.0; extra == 'docs'
Requires-Dist: pyenchant>=3.2; extra == 'docs'
Requires-Dist: scour>=0.38; extra == 'docs'
Requires-Dist: sphinx-autoapi>=2.1.0; extra == 'docs'
Requires-Dist: sphinx-copybutton>=0.5; extra == 'docs'
Requires-Dist: sphinx-design>=0.5; extra == 'docs'
Requires-Dist: sphinx>=8.2.3; extra == 'docs'
Requires-Dist: sphinxcontrib-images>=0.9; extra == 'docs'
Requires-Dist: sphinxcontrib-spelling>=8.0; extra == 'docs'
Requires-Dist: sphinxext-opengraph>=0.9; extra == 'docs'
